setup.py
WintxDriver_MySQLFabric.egg-info/PKG-INFO
WintxDriver_MySQLFabric.egg-info/SOURCES.txt
WintxDriver_MySQLFabric.egg-info/dependency_links.txt
WintxDriver_MySQLFabric.egg-info/namespace_packages.txt
WintxDriver_MySQLFabric.egg-info/requires.txt
WintxDriver_MySQLFabric.egg-info/top_level.txt
wintx/__init__.py
wintx/drivers/__init__.py
wintx/drivers/MySQLFabric/Config.py
wintx/drivers/MySQLFabric/Driver.py
wintx/drivers/MySQLFabric/__init__.py