Metadata-Version: 1.0
Name: WintxDriver-MySQLFabric
Version: 2.0.0-1
Summary: MySQL Fabric support for Wintx
Home-page: UNKNOWN
Author: Seth Cook
Author-email: sethcook@purdue.edu
License: UNKNOWN
Platform: UNKNOWN
Classifier: Programming Language :: Python :: 2.6
Classifier: Operating System :: Unix
Classifier: Development Status :: 5 - Production/Stable
